{
  "id": "4k_095",
  "source": "unsplash_4k_bulk_unique",
  "category": "4k",
  "title": "4K Curated Wallpaper 095",
  "description": "High-quality 4K curated wallpaper from Unsplash",
  "photographer": "NIR HIMI",
  "photographer_username": "nirhimi",
  "tags": [
    "4k",
    "wallpaper",
    "hd",
    "ultra high definition",
    "portrait",
    "mobile",
    "curated",
    "color-26260c"
  ],
  "unsplash_id": "6VXtsV_vRr4",
  "original_url": "https://unsplash.com/photos/palm-trees-reach-towards-the-sky-6VXtsV_vRr4",
  "download_url": "https://images.unsplash.com/photo-1747582598108-711679afdec1?ixid=M3wxMjA3fDB8MXxzZWFyY2h8OTV8fDRrJTIwd2FsbHBhcGVyfGVufDB8MXx8fDE3NTI2ODQyMTR8Mg&ixlib=rb-4.1.0&w=1080&h=1920&fit=crop&crop=center&q=85",
  "alt_text": "Palm trees reach towards the sky.",
  "width": 2292,
  "height": 4074,
  "color": "#26260c",
  "scraped_at": "2025-07-16T22:14:20.067273",
  "filename": "4k_095_6VXtsV_vRr4.jpg",
  "file_size": 727401,
  "quality": "4k_optimized"
}