{
  "id": "4k_167",
  "source": "unsplash_4k_bulk_unique",
  "category": "4k",
  "title": "4K Curated Wallpaper 167",
  "description": "High-quality 4K curated wallpaper from Unsplash",
  "photographer": "Eros Reyes Cabrera",
  "photographer_username": "eagraph",
  "tags": [
    "4k",
    "wallpaper",
    "hd",
    "ultra high definition",
    "portrait",
    "mobile",
    "curated",
    "color-8cc0c0"
  ],
  "unsplash_id": "BnhzaU-Qo80",
  "original_url": "https://unsplash.com/photos/an-aerial-view-of-the-water-and-land-BnhzaU-Qo80",
  "download_url": "https://images.unsplash.com/photo-1736291383577-c314937b0528?ixid=M3wxMjA3fDB8MXxzZWFyY2h8MTY3fHw0ayUyMHdhbGxwYXBlcnxlbnwwfDF8fHwxNzUyNjg0NDQ0fDI&ixlib=rb-4.1.0&w=1080&h=1920&fit=crop&crop=center&q=85",
  "alt_text": "An aerial view of the water and land",
  "width": 2250,
  "height": 4000,
  "color": "#8cc0c0",
  "scraped_at": "2025-07-16T22:17:42.516968",
  "filename": "4k_167_BnhzaU-Qo80.jpg",
  "file_size": 471696,
  "quality": "4k_optimized"
}