{
  "id": "seasonal_075",
  "category": "seasonal",
  "title": "Seasonal Wallpaper 075",
  "tags": [
    "seasonal",
    "wallpaper",
    "hd",
    "mobile"
  ],
  "urls": {
    "raw": "https://raw.githubusercontent.com/ddh4r4m/wallpaper-collection/main/collection/wallpapers/seasonal/075.jpg",
    "thumb": "https://raw.githubusercontent.com/ddh4r4m/wallpaper-collection/main/collection/thumbnails/seasonal/075.jpg"
  },
  "metadata": {
    "dimensions": {
      "width": 1080,
      "height": 1920
    },
    "file_size": 619574,
    "format": "JPEG",
    "added_at": "2025-07-17T00:04:43.260698",
    "hash": "c0d71daa1456926966effb78f8ac0bda",
    "source": "migrated"
  }
}