{
  "id": "anime_126",
  "category": "anime",
  "title": "The Oblivious Saint Can't Cont - Reddit AI",
  "tags": [
    "anime",
    "ai-generated",
    "hd",
    "mobile",
    "community"
  ],
  "metadata": {
    "dimensions": {
      "width": 1080,
      "height": 1339
    },
    "file_size": 224039,
    "format": "JPEG",
    "added_at": "2025-07-19T11:46:36.057845",
    "hash": "1b54fc73e3099bc1a2d9d497572fc0e6",
    "ai_source": "reddit",
    "ai_generated": true,
    "community_score": 515
  }
}