{
  "id": "nature_220",
  "category": "nature",
  "title": "Nature Wallpaper 220",
  "tags": [
    "nature",
    "wallpaper",
    "hd",
    "mobile"
  ],
  "urls": {
    "raw": "https://raw.githubusercontent.com/ddh4r4m/wallpaper-collection/main/collection/wallpapers/nature/220.jpg",
    "thumb": "https://raw.githubusercontent.com/ddh4r4m/wallpaper-collection/main/collection/thumbnails/nature/220.jpg"
  },
  "metadata": {
    "dimensions": {
      "width": 1080,
      "height": 1920
    },
    "file_size": 721470,
    "format": "JPEG",
    "added_at": "2025-07-17T00:04:26.819124",
    "hash": "17c6aef97f615b7be804c93e6994d5f0",
    "source": "migrated"
  }
}