{
  "id": "nature_241",
  "category": "nature",
  "title": "Nature Wallpaper 241",
  "tags": [
    "nature",
    "wallpaper",
    "hd",
    "mobile"
  ],
  "urls": {
    "raw": "https://raw.githubusercontent.com/ddh4r4m/wallpaper-collection/main/collection/wallpapers/nature/241.jpg",
    "thumb": "https://raw.githubusercontent.com/ddh4r4m/wallpaper-collection/main/collection/thumbnails/nature/241.jpg"
  },
  "metadata": {
    "dimensions": {
      "width": 1080,
      "height": 1920
    },
    "file_size": 268772,
    "format": "JPEG",
    "added_at": "2025-07-17T00:04:28.301684",
    "hash": "a18e6c6c2133175b9c9f23c637f9a338",
    "source": "migrated"
  }
}