{
  "id": "nature_291",
  "category": "nature",
  "title": "Mexican Hat, Utah [2404x3024]  - Reddit AI",
  "tags": [
    "nature",
    "ai-generated",
    "hd",
    "mobile",
    "community"
  ],
  "metadata": {
    "dimensions": {
      "width": 1080,
      "height": 1359
    },
    "file_size": 377873,
    "format": "JPEG",
    "added_at": "2025-07-18T00:29:04.940317",
    "hash": "599130655f44fca27fadfaf296ea5fed",
    "ai_source": "reddit",
    "ai_generated": true,
    "community_score": 1534
  }
}