{
  "id": "gaming_011",
  "category": "gaming",
  "title": "Gaming Wallpaper 011",
  "tags": [
    "gaming",
    "wallpaper",
    "hd",
    "mobile"
  ],
  "urls": {
    "raw": "https://raw.githubusercontent.com/ddh4r4m/wallpaper-collection/main/collection/wallpapers/gaming/011.jpg",
    "thumb": "https://raw.githubusercontent.com/ddh4r4m/wallpaper-collection/main/collection/thumbnails/gaming/011.jpg"
  },
  "metadata": {
    "dimensions": {
      "width": 1080,
      "height": 1920
    },
    "file_size": 33613,
    "format": "JPEG",
    "added_at": "2025-07-17T00:03:42.756167",
    "hash": "0959f93a810d06ee9c4fc2625d6db66a",
    "source": "migrated"
  }
}