{
  "id": "space_116",
  "category": "space",
  "title": "full length photo, sensual elite woman, - Civitai AI",
  "tags": [
    "space",
    "ai-generated",
    "civitai",
    "stable-diffusion",
    "hd",
    "mobile",
    "community-rated"
  ],
  "metadata": {
    "dimensions": {
      "width": 832,
      "height": 1216
    },
    "file_size": 141585,
    "format": "JPEG",
    "added_at": "2025-07-19T11:59:37.755005",
    "hash": "a20f7c27675bdd0da797d50d94a8ebc0",
    "ai_source": "civitai",
    "ai_generated": true,
    "source_platform": "civitai.com",
    "ai_prompt": "full length photo, sensual elite woman, sexy attire, photorealistic, glamour photography, artistic photo, seductive adult woman, sensual fashionista woman, sexy long grey hair with dark highlights, go",
    "civitai_stats": {
      "cryCount": 9,
      "laughCount": 14,
      "likeCount": 139,
      "dislikeCount": 0,
      "heartCount": 57,
      "commentCount": 0
    }
  }
}