{
  "id": "minimal_015",
  "category": "minimal",
  "title": "Minimal Wallpaper 015",
  "tags": [
    "minimal",
    "wallpaper",
    "hd",
    "mobile"
  ],
  "urls": {
    "raw": "https://raw.githubusercontent.com/ddh4r4m/wallpaper-collection/main/collection/wallpapers/minimal/015.jpg",
    "thumb": "https://raw.githubusercontent.com/ddh4r4m/wallpaper-collection/main/collection/thumbnails/minimal/015.jpg"
  },
  "metadata": {
    "dimensions": {
      "width": 1080,
      "height": 1920
    },
    "file_size": 92870,
    "format": "JPEG",
    "added_at": "2025-07-17T00:04:03.103877",
    "hash": "75c396fc2ccfd2f75d1e45e70bd2080b",
    "source": "migrated"
  }
}