{
  "id": "abstract_059",
  "category": "abstract",
  "title": "Abstract Wallpaper 059",
  "tags": [
    "abstract",
    "wallpaper",
    "hd",
    "mobile"
  ],
  "urls": {
    "raw": "https://raw.githubusercontent.com/ddh4r4m/wallpaper-collection/main/collection/wallpapers/abstract/059.jpg",
    "thumb": "https://raw.githubusercontent.com/ddh4r4m/wallpaper-collection/main/collection/thumbnails/abstract/059.jpg"
  },
  "metadata": {
    "dimensions": {
      "width": 1080,
      "height": 1920
    },
    "file_size": 397693,
    "format": "JPEG",
    "added_at": "2025-07-17T00:02:16.232329",
    "hash": "388e38b28b98c0cc98169fbef133bb93",
    "source": "migrated"
  }
}