{
  "meta": {
    "version": "1.0",
    "generated_at": "2025-07-28T23:12:02.393375",
    "page": 128,
    "per_page": 15,
    "total_pages": 183,
    "total_count": 2743,
    "count_on_page": 15,
    "categories": 22,
    "has_next": true,
    "has_prev": true,
    "next_page_url": "/api/v1/all/pages/129.json",
    "prev_page_url": "/api/v1/all/pages/127.json"
  },
  "data": [
    {
      "id": "nature_223",
      "category": "nature",
      "title": "Nature Wallpaper 223",
      "tags": [
        "nature",
        "wallpaper",
        "hd",
        "mobile"
      ],
      "urls": {
        "raw": "https://media.githubusercontent.com/media/ddh4r4m/wallpaper-collection/main/collection/wallpapers/nature/223.jpg",
        "thumb": "https://media.githubusercontent.com/media/ddh4r4m/wallpaper-collection/main/collection/thumbnails/nature/223.jpg"
      },
      "metadata": {
        "dimensions": {
          "width": 1080,
          "height": 1920
        },
        "file_size": 483420,
        "format": "JPEG",
        "added_at": "2025-07-17T00:04:27.013431",
        "hash": "fd6591621a6347c2cce7cfbeb012f758",
        "source": "migrated"
      }
    },
    {
      "id": "nature_224",
      "category": "nature",
      "title": "Nature Wallpaper 224",
      "tags": [
        "nature",
        "wallpaper",
        "hd",
        "mobile"
      ],
      "urls": {
        "raw": "https://media.githubusercontent.com/media/ddh4r4m/wallpaper-collection/main/collection/wallpapers/nature/224.jpg",
        "thumb": "https://media.githubusercontent.com/media/ddh4r4m/wallpaper-collection/main/collection/thumbnails/nature/224.jpg"
      },
      "metadata": {
        "dimensions": {
          "width": 1080,
          "height": 1920
        },
        "file_size": 293661,
        "format": "JPEG",
        "added_at": "2025-07-17T00:04:27.071329",
        "hash": "fdbcb446c9ff774dcb02d59ce7c19feb",
        "source": "migrated"
      }
    },
    {
      "id": "nature_225",
      "category": "nature",
      "title": "Nature Wallpaper 225",
      "tags": [
        "nature",
        "wallpaper",
        "hd",
        "mobile"
      ],
      "urls": {
        "raw": "https://media.githubusercontent.com/media/ddh4r4m/wallpaper-collection/main/collection/wallpapers/nature/225.jpg",
        "thumb": "https://media.githubusercontent.com/media/ddh4r4m/wallpaper-collection/main/collection/thumbnails/nature/225.jpg"
      },
      "metadata": {
        "dimensions": {
          "width": 1080,
          "height": 1920
        },
        "file_size": 462699,
        "format": "JPEG",
        "added_at": "2025-07-17T00:04:27.135711",
        "hash": "d27aeb6afc17c93020d44b59a9c84637",
        "source": "migrated"
      }
    },
    {
      "id": "nature_226",
      "category": "nature",
      "title": "Nature Wallpaper 226",
      "tags": [
        "nature",
        "wallpaper",
        "hd",
        "mobile"
      ],
      "urls": {
        "raw": "https://media.githubusercontent.com/media/ddh4r4m/wallpaper-collection/main/collection/wallpapers/nature/226.jpg",
        "thumb": "https://media.githubusercontent.com/media/ddh4r4m/wallpaper-collection/main/collection/thumbnails/nature/226.jpg"
      },
      "metadata": {
        "dimensions": {
          "width": 1080,
          "height": 1920
        },
        "file_size": 462094,
        "format": "JPEG",
        "added_at": "2025-07-17T00:04:27.203559",
        "hash": "86ed736bdf1c538b54600de0d05e0a27",
        "source": "migrated"
      }
    },
    {
      "id": "nature_227",
      "category": "nature",
      "title": "Nature Wallpaper 227",
      "tags": [
        "nature",
        "wallpaper",
        "hd",
        "mobile"
      ],
      "urls": {
        "raw": "https://media.githubusercontent.com/media/ddh4r4m/wallpaper-collection/main/collection/wallpapers/nature/227.jpg",
        "thumb": "https://media.githubusercontent.com/media/ddh4r4m/wallpaper-collection/main/collection/thumbnails/nature/227.jpg"
      },
      "metadata": {
        "dimensions": {
          "width": 1080,
          "height": 1920
        },
        "file_size": 656772,
        "format": "JPEG",
        "added_at": "2025-07-17T00:04:27.282680",
        "hash": "0923622751097d357b4ab86693bc58de",
        "source": "migrated"
      }
    },
    {
      "id": "nature_228",
      "category": "nature",
      "title": "Nature Wallpaper 228",
      "tags": [
        "nature",
        "wallpaper",
        "hd",
        "mobile"
      ],
      "urls": {
        "raw": "https://media.githubusercontent.com/media/ddh4r4m/wallpaper-collection/main/collection/wallpapers/nature/228.jpg",
        "thumb": "https://media.githubusercontent.com/media/ddh4r4m/wallpaper-collection/main/collection/thumbnails/nature/228.jpg"
      },
      "metadata": {
        "dimensions": {
          "width": 1080,
          "height": 1920
        },
        "file_size": 289930,
        "format": "JPEG",
        "added_at": "2025-07-17T00:04:27.339459",
        "hash": "a0640fb4f99a8c6a752069efe820112c",
        "source": "migrated"
      }
    },
    {
      "id": "nature_229",
      "category": "nature",
      "title": "Nature Wallpaper 229",
      "tags": [
        "nature",
        "wallpaper",
        "hd",
        "mobile"
      ],
      "urls": {
        "raw": "https://media.githubusercontent.com/media/ddh4r4m/wallpaper-collection/main/collection/wallpapers/nature/229.jpg",
        "thumb": "https://media.githubusercontent.com/media/ddh4r4m/wallpaper-collection/main/collection/thumbnails/nature/229.jpg"
      },
      "metadata": {
        "dimensions": {
          "width": 1080,
          "height": 1920
        },
        "file_size": 601054,
        "format": "JPEG",
        "added_at": "2025-07-17T00:04:27.413355",
        "hash": "e71a8c1fcdf2e93e8030bd44deee3e34",
        "source": "migrated"
      }
    },
    {
      "id": "nature_230",
      "category": "nature",
      "title": "Nature Wallpaper 230",
      "tags": [
        "nature",
        "wallpaper",
        "hd",
        "mobile"
      ],
      "urls": {
        "raw": "https://media.githubusercontent.com/media/ddh4r4m/wallpaper-collection/main/collection/wallpapers/nature/230.jpg",
        "thumb": "https://media.githubusercontent.com/media/ddh4r4m/wallpaper-collection/main/collection/thumbnails/nature/230.jpg"
      },
      "metadata": {
        "dimensions": {
          "width": 1080,
          "height": 1920
        },
        "file_size": 734580,
        "format": "JPEG",
        "added_at": "2025-07-17T00:04:27.492668",
        "hash": "f9ddf80f491e4d2e5023d325a025493c",
        "source": "migrated"
      }
    },
    {
      "id": "nature_231",
      "category": "nature",
      "title": "Nature Wallpaper 231",
      "tags": [
        "nature",
        "wallpaper",
        "hd",
        "mobile"
      ],
      "urls": {
        "raw": "https://media.githubusercontent.com/media/ddh4r4m/wallpaper-collection/main/collection/wallpapers/nature/231.jpg",
        "thumb": "https://media.githubusercontent.com/media/ddh4r4m/wallpaper-collection/main/collection/thumbnails/nature/231.jpg"
      },
      "metadata": {
        "dimensions": {
          "width": 1080,
          "height": 1920
        },
        "file_size": 594991,
        "format": "JPEG",
        "added_at": "2025-07-17T00:04:27.566510",
        "hash": "7197d2fae7b51ab29bfb775fd0ad80e2",
        "source": "migrated"
      }
    },
    {
      "id": "nature_232",
      "category": "nature",
      "title": "Nature Wallpaper 232",
      "tags": [
        "nature",
        "wallpaper",
        "hd",
        "mobile"
      ],
      "urls": {
        "raw": "https://media.githubusercontent.com/media/ddh4r4m/wallpaper-collection/main/collection/wallpapers/nature/232.jpg",
        "thumb": "https://media.githubusercontent.com/media/ddh4r4m/wallpaper-collection/main/collection/thumbnails/nature/232.jpg"
      },
      "metadata": {
        "dimensions": {
          "width": 1080,
          "height": 1920
        },
        "file_size": 599781,
        "format": "JPEG",
        "added_at": "2025-07-17T00:04:27.640073",
        "hash": "7c8d1f6fc80bb43ca2eedcd7c0ba5381",
        "source": "migrated"
      }
    },
    {
      "id": "nature_233",
      "category": "nature",
      "title": "Nature Wallpaper 233",
      "tags": [
        "nature",
        "wallpaper",
        "hd",
        "mobile"
      ],
      "urls": {
        "raw": "https://media.githubusercontent.com/media/ddh4r4m/wallpaper-collection/main/collection/wallpapers/nature/233.jpg",
        "thumb": "https://media.githubusercontent.com/media/ddh4r4m/wallpaper-collection/main/collection/thumbnails/nature/233.jpg"
      },
      "metadata": {
        "dimensions": {
          "width": 1080,
          "height": 1920
        },
        "file_size": 723327,
        "format": "JPEG",
        "added_at": "2025-07-17T00:04:27.717907",
        "hash": "12289d64712efd37acca5576457471b1",
        "source": "migrated"
      }
    },
    {
      "id": "nature_234",
      "category": "nature",
      "title": "Nature Wallpaper 234",
      "tags": [
        "nature",
        "wallpaper",
        "hd",
        "mobile"
      ],
      "urls": {
        "raw": "https://media.githubusercontent.com/media/ddh4r4m/wallpaper-collection/main/collection/wallpapers/nature/234.jpg",
        "thumb": "https://media.githubusercontent.com/media/ddh4r4m/wallpaper-collection/main/collection/thumbnails/nature/234.jpg"
      },
      "metadata": {
        "dimensions": {
          "width": 1080,
          "height": 1920
        },
        "file_size": 876493,
        "format": "JPEG",
        "added_at": "2025-07-17T00:04:27.804822",
        "hash": "d72d173f7bbae23b5b5cd978b0851c16",
        "source": "migrated"
      }
    },
    {
      "id": "nature_235",
      "category": "nature",
      "title": "Nature Wallpaper 235",
      "tags": [
        "nature",
        "wallpaper",
        "hd",
        "mobile"
      ],
      "urls": {
        "raw": "https://media.githubusercontent.com/media/ddh4r4m/wallpaper-collection/main/collection/wallpapers/nature/235.jpg",
        "thumb": "https://media.githubusercontent.com/media/ddh4r4m/wallpaper-collection/main/collection/thumbnails/nature/235.jpg"
      },
      "metadata": {
        "dimensions": {
          "width": 1080,
          "height": 1920
        },
        "file_size": 419086,
        "format": "JPEG",
        "added_at": "2025-07-17T00:04:27.869097",
        "hash": "0945a9ab28a1c7733c1535da3b09e08a",
        "source": "migrated"
      }
    },
    {
      "id": "nature_236",
      "category": "nature",
      "title": "Nature Wallpaper 236",
      "tags": [
        "nature",
        "wallpaper",
        "hd",
        "mobile"
      ],
      "urls": {
        "raw": "https://media.githubusercontent.com/media/ddh4r4m/wallpaper-collection/main/collection/wallpapers/nature/236.jpg",
        "thumb": "https://media.githubusercontent.com/media/ddh4r4m/wallpaper-collection/main/collection/thumbnails/nature/236.jpg"
      },
      "metadata": {
        "dimensions": {
          "width": 1080,
          "height": 1920
        },
        "file_size": 746371,
        "format": "JPEG",
        "added_at": "2025-07-17T00:04:27.949152",
        "hash": "ac118048345995a1edec93db71d0d689",
        "source": "migrated"
      }
    },
    {
      "id": "nature_237",
      "category": "nature",
      "title": "Nature Wallpaper 237",
      "tags": [
        "nature",
        "wallpaper",
        "hd",
        "mobile"
      ],
      "urls": {
        "raw": "https://media.githubusercontent.com/media/ddh4r4m/wallpaper-collection/main/collection/wallpapers/nature/237.jpg",
        "thumb": "https://media.githubusercontent.com/media/ddh4r4m/wallpaper-collection/main/collection/thumbnails/nature/237.jpg"
      },
      "metadata": {
        "dimensions": {
          "width": 1080,
          "height": 1920
        },
        "file_size": 411301,
        "format": "JPEG",
        "added_at": "2025-07-17T00:04:28.012501",
        "hash": "fe6914f1a5ce6978385eb1dc382a8a4e",
        "source": "migrated"
      }
    }
  ]
}