{
  "id": "ai_067",
  "category": "ai",
  "title": "Ai Premium AI - Civitai",
  "tags": [
    "ai",
    "ai-generated",
    "civitai",
    "stable-diffusion",
    "hd",
    "mobile",
    "viral",
    "community-rated"
  ],
  "metadata": {
    "dimensions": {
      "width": 832,
      "height": 1216
    },
    "file_size": 132485,
    "format": "JPEG",
    "added_at": "2025-07-19T12:26:27.105078",
    "hash": "1e7b39ca527dbcb9b9218191e797b82c",
    "ai_source": "civitai",
    "ai_generated": true,
    "source_platform": "civitai.com",
    "scraping_method": "scroll_based",
    "civitai_tag_id": 4,
    "civitai_stats": {
      "cryCount": 204,
      "laughCount": 301,
      "likeCount": 2721,
      "dislikeCount": 0,
      "heartCount": 923,
      "commentCount": 1
    },
    "total_reactions": 3644
  }
}