{
  "id": "space_032",
  "source": "wallhaven",
  "category": "space",
  "title": "Space Wallpaper 32",
  "description": "High-quality space wallpaper from wallhaven",
  "width": 1080,
  "height": 1920,
  "photographer": "Wallhaven Contributor",
  "tags": [
    "space",
    "wallpaper",
    "hd",
    "high resolution",
    "mobile"
  ],
  "download_url": "https://w.wallhaven.cc/full/j3/wallhaven-j3x6gm.jpg",
  "source_url": "https://w.wallhaven.cc/full/j3/wallhaven-j3x6gm.jpg",
  "original_info": {
    "id": "wallhaven_j3x6gm",
    "url": "https://w.wallhaven.cc/full/j3/wallhaven-j3x6gm.jpg",
    "source": "wallhaven",
    "photographer": "Wallhaven Contributor",
    "alt": "galaxy wallpaper",
    "width": 3222,
    "height": 3703
  },
  "crawled_at": "2025-07-14T20:59:30.203883Z"
}