{
  "id": "architecture_082",
  "category": "architecture",
  "title": "Architecture Wallpaper 082",
  "tags": [
    "architecture",
    "wallpaper",
    "hd",
    "mobile"
  ],
  "urls": {
    "raw": "https://raw.githubusercontent.com/ddh4r4m/wallpaper-collection/main/collection/wallpapers/architecture/082.jpg",
    "thumb": "https://raw.githubusercontent.com/ddh4r4m/wallpaper-collection/main/collection/thumbnails/architecture/082.jpg"
  },
  "metadata": {
    "dimensions": {
      "width": 1080,
      "height": 1920
    },
    "file_size": 327968,
    "format": "JPEG",
    "added_at": "2025-07-17T00:02:50.046050",
    "hash": "228adcb75b6ef6d43d36613ba833a91d",
    "source": "migrated"
  }
}