{
  "id": "architecture_186",
  "category": "architecture",
  "title": "Architecture Wallpaper 186",
  "tags": [
    "architecture",
    "wallpaper",
    "hd",
    "mobile"
  ],
  "urls": {
    "raw": "https://raw.githubusercontent.com/ddh4r4m/wallpaper-collection/main/collection/wallpapers/architecture/186.jpg",
    "thumb": "https://raw.githubusercontent.com/ddh4r4m/wallpaper-collection/main/collection/thumbnails/architecture/186.jpg"
  },
  "metadata": {
    "dimensions": {
      "width": 1080,
      "height": 1920
    },
    "file_size": 326998,
    "format": "JPEG",
    "added_at": "2025-07-17T00:02:56.350344",
    "hash": "f07fac767c99b61629c54496484f2e32",
    "source": "migrated"
  }
}